{"assembly":[{"glue_to":[],"part":0,"step":1},{"glue_to":[],"part":1,"step":2},{"glue_to":[],"part":2,"step":3},{"glue_to":[],"part":3,"step":4},{"glue_to":[],"part":4,"step":5},{"glue_to":[],"part":5,"step":6},{"glue_to":[],"part":6,"step":7},{"glue_to":[],"part":7,"step":8},{"glue_to":[],"part":8,"step":9},{"glue_to":[],"part":9,"step":10},{"glue_to":[],"part":10,"step":11},{"glue_to":[],"part":11,"step":12}],"metadata":{"below_min_size":false,"buildable":true,"clearance_mm":0.25,"design":true,"detail":2,"difficulty_tier":"2","est_minutes":44,"finished_mm":142.0,"fit_scale":0.9466,"margin_mm":[5.0,5.0],"min_finished_mm":50.0,"min_tab_sum_floor_mm":25.0,"min_tab_sum_mm":11.1,"n_deferred":0,"n_islands":12,"n_pages":12,"n_seams":48,"n_tabs":48,"oversize_parts":0,"page_mm":[210.0,297.0],"paper":"A4","printable_mm":[200.0,287.0],"scale_mm":150.0,"shape":"d:gyeongbok","stars":3,"sub_min_tabs":0,"tab_below_min":true},"part_nets":[{"cut_edges":[[0,1],[0,4],[1,3],[2,6],[3,7],[4,6],[6,7]],"faces":[{"face_id":0,"vert_ids":[1,3,0],"verts":[[6.6262,245.4289],[6.6262,148.617],[22.7616,245.4289]]},{"face_id":2,"vert_ids":[0,3,2],"verts":[[22.7616,245.4289],[6.6262,148.617],[22.7616,148.617]]},{"face_id":3,"vert_ids":[2,4,0],"verts":[[22.7616,148.617],[164.7524,245.4289],[22.7616,245.4289]]},{"face_id":7,"vert_ids":[3,7,2],"verts":[[6.6262,148.617],[6.6262,6.6262],[22.7616,148.617]]},{"face_id":8,"vert_ids":[6,4,2],"verts":[[164.7524,148.617],[164.7524,245.4289],[22.7616,148.617]]},{"face_id":9,"vert_ids":[2,7,6],"verts":[[22.7616,148.617],[6.6262,6.6262],[22.7616,6.6262]]}],"fold_convex":[true,true,true,true,true],"fold_edges":[[0,2],[0,3],[2,3],[2,4],[2,7]],"full_h":252.8027,"full_w":172.1262,"h":238.8027,"index":0,"n_faces":6,"n_tabs":5,"tabs":[{"edge":[0,1],"height_mm":7.0,"kind":"flap","number":1,"poly":[[22.7616,245.4289],[20.3411,252.4289],[9.0465,252.4289],[6.6262,245.4289]]},{"edge":[1,3],"height_mm":7.0,"kind":"flap","number":2,"poly":[[6.6262,245.4289],[-0.3738,230.9071],[-0.3738,163.1388],[6.6262,148.617]]},{"edge":[2,6],"height_mm":7.0,"kind":"flap","number":3,"poly":[[22.7616,148.617],[44.0602,141.617],[143.4538,141.617],[164.7524,148.617]]},{"edge":[4,6],"height_mm":7.0,"kind":"flap","number":4,"poly":[[164.7524,245.4289],[171.7524,230.9071],[171.7524,163.1388],[164.7524,148.617]]},{"edge":[6,7],"height_mm":7.0,"kind":"flap","number":5,"poly":[[22.7616,6.6262],[20.3411,-0.3738],[9.0465,-0.3738],[6.6262,6.6262]]}],"w":158.1262},{"cut_edges":[[8,9],[8,12],[9,11],[9,13],[11,15],[12,14],[14,15]],"faces":[{"face_id":1,"vert_ids":[12,9,8],"verts":[[168.0459,142.9047],[168.0459,0.0],[184.0781,1.8218]]},{"face_id":4,"vert_ids":[9,15,11],"verts":[[10.931,125.0506],[141.0828,237.2756],[0.0,221.2435]]},{"face_id":5,"vert_ids":[13,9,12],"verts":[[152.0138,141.0828],[168.0459,0.0],[168.0459,142.9047]]},{"face_id":6,"vert_ids":[13,15,9],"verts":[[152.0138,141.0828],[141.0828,237.2756],[10.931,125.0506]]},{"face_id":10,"vert_ids":[14,13,12],"verts":[[157.1149,239.0975],[152.0138,141.0828],[168.0459,142.9047]]},{"face_id":11,"vert_ids":[15,13,14],"verts":[[141.0828,237.2756],[152.0138,141.0828],[157.1149,239.0975]]}],"fold_convex":[true,true,true,true,true],"fold_edges":[[9,12],[9,15],[12,13],[13,14],[13,15]],"full_h":241.826,"full_w":188.6285,"h":239.0975,"index":1,"n_faces":6,"n_tabs":3,"tabs":[{"edge":[8,12],"height_mm":7.0,"kind":"flap","number":6,"poly":[[184.0781,1.8218],[188.6285,23.7746],[177.406,122.5326],[168.0459,142.9047]]},{"edge":[9,13],"height_mm":7.0,"kind":"flap","number":7,"poly":[[168.0459,0.0],[158.6858,20.3721],[147.4633,119.13],[152.0137,141.0828]]},{"edge":[11,15],"height_mm":7.0,"kind":"flap","number":8,"poly":[[0.0,221.2435],[20.372,230.6035],[119.13,241.826],[141.0828,237.2756]]}],"w":184.0781},{"cut_edges":[[16,17],[16,20],[17,19],[18,22],[19,23],[20,22],[22,23]],"faces":[{"face_id":12,"vert_ids":[17,19,16],"verts":[[6.6262,6.6262],[77.6216,6.6262],[6.6262,58.2593]]},{"face_id":14,"vert_ids":[16,19,18],"verts":[[6.6262,58.2593],[77.6216,6.6262],[77.6216,58.2593]]},{"face_id":15,"vert_ids":[18,20,16],"verts":[[77.6216,58.2593],[6.6262,167.9794],[6.6262,58.2593]]},{"face_id":19,"vert_ids":[19,23,18],"verts":[[77.6216,6.6262],[187.3418,6.6262],[77.6216,58.2593]]},{"face_id":20,"vert_ids":[22,20,18],"verts":[[77.6216,167.9794],[6.6262,167.9794],[77.6216,58.2593]]},{"face_id":21,"vert_ids":[18,23,22],"verts":[[77.6216,58.2593],[187.3418,6.6262],[187.3418,58.2593]]}],"fold_convex":[true,true,true,true,true],"fold_edges":[[16,18],[16,19],[18,19],[18,20],[18,23]],"full_h":175.3532,"full_w":194.7156,"h":161.3532,"index":2,"n_faces":6,"n_tabs":5,"tabs":[{"edge":[16,17],"height_mm":7.0,"kind":"flap","number":9,"poly":[[6.6262,58.2593],[-0.3738,50.5143],[-0.3738,14.3712],[6.6262,6.6262]]},{"edge":[17,19],"height_mm":7.0,"kind":"flap","number":10,"poly":[[6.6262,6.6262],[17.2755,-0.3738],[66.9723,-0.3738],[77.6216,6.6262]]},{"edge":[18,22],"height_mm":7.0,"kind":"flap","number":11,"poly":[[77.6216,58.2593],[84.6216,74.7173],[84.6216,151.5214],[77.6216,167.9794]]},{"edge":[20,22],"height_mm":7.0,"kind":"flap","number":12,"poly":[[6.6262,167.9794],[17.2755,174.9794],[66.9723,174.9794],[77.6216,167.9794]]},{"edge":[22,23],"height_mm":7.0,"kind":"flap","number":13,"poly":[[187.3418,58.2593],[194.3418,50.5143],[194.3418,14.3712],[187.3418,6.6262]]}],"w":180.7156},{"cut_edges":[[24,25],[24,28],[25,27],[25,29],[27,31],[28,30],[30,31]],"faces":[{"face_id":13,"vert_ids":[28,25,24],"verts":[[64.238,176.225],[185.5,176.225],[163.5148,222.9435]]},{"face_id":16,"vert_ids":[25,31,27],"verts":[[132.9416,30.2297],[21.9852,99.2768],[68.7037,0.0]]},{"face_id":17,"vert_ids":[29,25,28],"verts":[[86.2232,129.5065],[185.5,176.225],[64.238,176.225]]},{"face_id":18,"vert_ids":[29,31,25],"verts":[[86.2232,129.5065],[21.9852,99.2768],[132.9416,30.2297]]},{"face_id":22,"vert_ids":[30,29,28],"verts":[[0.0,145.9954],[86.2232,129.5065],[64.238,176.225]]},{"face_id":23,"vert_ids":[31,29,30],"verts":[[21.9852,99.2768],[86.2232,129.5065],[0.0,145.9954]]}],"fold_convex":[true,true,true,true,true],"fold_edges":[[25,28],[25,31],[28,29],[29,30],[29,31]],"full_h":222.9435,"full_w":185.5,"h":222.9435,"index":3,"n_faces":6,"n_tabs":3,"tabs":[{"edge":[24,28],"height_mm":7.0,"kind":"flap","number":14,"poly":[[163.5148,222.9434],[145.6426,222.2693],[76.1489,189.5665],[64.238,176.225]]},{"edge":[25,29],"height_mm":7.0,"kind":"flap","number":15,"poly":[[185.5,176.225],[173.589,162.8835],[104.0953,130.1805],[86.2232,129.5065]]},{"edge":[27,31],"height_mm":7.0,"kind":"flap","number":16,"poly":[[68.7037,0.0],[55.3622,11.911],[22.6592,81.4047],[21.9852,99.2768]]}],"w":185.5},{"cut_edges":[[32,33],[32,36],[33,35],[34,38],[35,39],[36,38],[38,39]],"faces":[{"face_id":24,"vert_ids":[33,35,32],"verts":[[6.6262,231.7031],[6.6262,141.3454],[12.435,231.7031]]},{"face_id":26,"vert_ids":[32,35,34],"verts":[[12.435,231.7031],[6.6262,141.3454],[12.435,141.3454]]},{"face_id":27,"vert_ids":[34,36,32],"verts":[[12.435,141.3454],[147.9716,231.7031],[12.435,231.7031]]},{"face_id":31,"vert_ids":[35,39,34],"verts":[[6.6262,141.3454],[6.6262,5.8087],[12.435,141.3454]]},{"face_id":32,"vert_ids":[38,36,34],"verts":[[147.9716,141.3454],[147.9716,231.7031],[12.435,141.3454]]},{"face_id":33,"vert_ids":[34,39,38],"verts":[[12.435,141.3454],[6.6262,5.8087],[12.435,5.8087]]}],"fold_convex":[true,true,true,true,true],"fold_edges":[[32,34],[32,35],[34,35],[34,36],[34,39]],"full_h":232.6944,"full_w":155.3454,"h":225.8944,"index":4,"n_faces":6,"n_tabs":5,"tabs":[{"edge":[32,33],"height_mm":3.4,"kind":"flap","number":17,"poly":[[12.435,231.7031],[11.5636,235.1031],[7.4976,235.1031],[6.6262,231.7031]]},{"edge":[33,35],"height_mm":7.0,"kind":"flap","number":18,"poly":[[6.6262,231.7031],[-0.3738,218.1495],[-0.3738,154.899],[6.6262,141.3454]]},{"edge":[34,38],"height_mm":7.0,"kind":"flap","number":19,"poly":[[12.435,141.3454],[32.7653,134.3454],[127.6411,134.3454],[147.9716,141.3454]]},{"edge":[36,38],"height_mm":7.0,"kind":"flap","number":20,"poly":[[147.9716,231.7031],[154.9716,218.1495],[154.9716,154.899],[147.9716,141.3454]]},{"edge":[38,39],"height_mm":3.4,"kind":"flap","number":21,"poly":[[12.435,5.8087],[11.5636,2.4087],[7.4976,2.4087],[6.6262,5.8087]]}],"w":141.3454},{"cut_edges":[[40,41],[40,44],[41,43],[41,45],[43,47],[44,46],[46,47]],"faces":[{"face_id":25,"vert_ids":[44,41,40],"verts":[[145.0847,135.6611],[145.0847,0.0],[150.888,0.2488]]},{"face_id":28,"vert_ids":[41,47,43],"verts":[[3.869,129.609],[135.4124,225.6874],[0.0,219.8839]]},{"face_id":29,"vert_ids":[45,41,44],"verts":[[139.2813,135.4125],[145.0847,0.0],[145.0847,135.6611]]},{"face_id":30,"vert_ids":[45,47,41],"verts":[[139.2813,135.4125],[135.4124,225.6874],[3.869,129.609]]},{"face_id":34,"vert_ids":[46,45,44],"verts":[[141.2157,225.936],[139.2813,135.4125],[145.0847,135.6611]]},{"face_id":35,"vert_ids":[47,45,46],"verts":[[135.4124,225.6874],[139.2813,135.4125],[141.2157,225.936]]}],"fold_convex":[true,true,true,true,true],"fold_edges":[[41,44],[41,47],[44,45],[45,46],[45,47]],"full_h":231.8105,"full_w":157.0111,"h":225.936,"index":5,"n_faces":6,"n_tabs":3,"tabs":[{"edge":[40,44],"height_mm":7.0,"kind":"flap","number":22,"poly":[[150.888,0.2488],[157.0111,20.8603],[152.9488,115.649],[145.0847,135.6611]]},{"edge":[41,45],"height_mm":7.0,"kind":"flap","number":23,"poly":[[145.0847,0.0],[137.2206,20.0122],[133.1582,114.8009],[139.2813,135.4125]]},{"edge":[43,47],"height_mm":7.0,"kind":"flap","number":24,"poly":[[0.0,219.8839],[20.0121,227.748],[114.8008,231.8105],[135.4124,225.6874]]}],"w":150.888},{"cut_edges":[[49,53],[50,53],[51,52],[52,53]],"faces":[{"face_id":36,"vert_ids":[49,48,51],"verts":[[63.306,56.0218],[119.3278,56.0218],[119.3278,112.0436]]},{"face_id":37,"vert_ids":[49,51,50],"verts":[[63.306,56.0218],[119.3278,112.0436],[59.0718,116.278]]},{"face_id":38,"vert_ids":[51,48,52],"verts":[[119.3278,112.0436],[119.3278,56.0218],[175.3497,56.0218]]},{"face_id":39,"vert_ids":[51,52,50],"verts":[[119.3278,112.0436],[71.6913,175.3497],[59.0718,116.278]]},{"face_id":40,"vert_ids":[52,48,53],"verts":[[175.3497,56.0218],[119.3278,56.0218],[119.3278,0.0]]},{"face_id":41,"vert_ids":[52,53,50],"verts":[[71.6913,175.3497],[2.3454,137.0348],[59.0718,116.278]]},{"face_id":42,"vert_ids":[53,48,49],"verts":[[119.3278,0.0],[119.3278,56.0218],[63.306,56.0218]]},{"face_id":43,"vert_ids":[53,49,50],"verts":[[0.0,103.6583],[63.306,56.0218],[59.0718,116.278]]}],"fold_convex":[true,true,true,true,true,true,true,true],"fold_edges":[[48,49],[48,51],[48,52],[48,53],[49,50],[49,51],[50,51],[50,52]],"full_h":175.3497,"full_w":175.3497,"h":175.3497,"index":6,"n_faces":8,"n_tabs":4,"tabs":[{"edge":[49,53],"height_mm":7.0,"kind":"flap","number":25,"poly":[[63.306,56.0218],[66.7595,42.6688],[105.9748,3.4535],[119.3278,0.0]]},{"edge":[50,53],"height_mm":7.0,"kind":"flap","number":26,"poly":[[59.0718,116.2779],[39.6483,115.9313],[16.9579,124.234],[2.3454,137.0348]]},{"edge":[51,52],"height_mm":7.0,"kind":"flap","number":27,"poly":[[119.3278,112.0436],[132.6808,108.5901],[171.8961,69.3748],[175.3496,56.0218]]},{"edge":[52,53],"height_mm":7.0,"kind":"flap","number":28,"poly":[[175.3496,56.0218],[171.8962,42.6689],[132.6808,3.4535],[119.3278,0.0]]}],"w":175.3497},{"cut_edges":[[54,55],[54,58],[55,57],[56,60],[57,61],[58,60],[60,61]],"faces":[{"face_id":44,"vert_ids":[55,57,54],"verts":[[6.6262,6.6262],[64.7133,6.6262],[6.6262,38.8969]]},{"face_id":46,"vert_ids":[54,57,56],"verts":[[6.6262,38.8969],[64.7133,6.6262],[64.7133,38.8969]]},{"face_id":47,"vert_ids":[56,58,54],"verts":[[64.7133,38.8969],[6.6262,129.2547],[6.6262,38.8969]]},{"face_id":51,"vert_ids":[57,61,56],"verts":[[64.7133,6.6262],[155.0712,6.6262],[64.7133,38.8969]]},{"face_id":52,"vert_ids":[60,58,56],"verts":[[64.7133,129.2547],[6.6262,129.2547],[64.7133,38.8969]]},{"face_id":53,"vert_ids":[56,61,60],"verts":[[64.7133,38.8969],[155.0712,6.6262],[155.0712,38.8969]]}],"fold_convex":[true,true,true,true,true],"fold_edges":[[54,56],[54,57],[56,57],[56,58],[56,61]],"full_h":136.6285,"full_w":162.445,"h":122.6285,"index":7,"n_faces":6,"n_tabs":5,"tabs":[{"edge":[54,55],"height_mm":7.0,"kind":"flap","number":29,"poly":[[6.6262,38.8969],[-0.3738,34.0563],[-0.3738,11.4668],[6.6262,6.6262]]},{"edge":[55,57],"height_mm":7.0,"kind":"flap","number":30,"poly":[[6.6262,6.6262],[15.3394,-0.3738],[56.0003,-0.3738],[64.7133,6.6262]]},{"edge":[56,60],"height_mm":7.0,"kind":"flap","number":31,"poly":[[64.7133,38.8969],[71.7133,52.4504],[71.7133,115.701],[64.7133,129.2547]]},{"edge":[58,60],"height_mm":7.0,"kind":"flap","number":32,"poly":[[6.6262,129.2547],[15.3394,136.2547],[56.0003,136.2547],[64.7133,129.2547]]},{"edge":[60,61],"height_mm":7.0,"kind":"flap","number":33,"poly":[[155.0712,38.8969],[162.0712,34.0563],[162.0712,11.4668],[155.0712,6.6262]]}],"w":148.445},{"cut_edges":[[62,63],[62,66],[63,65],[63,67],[65,69],[66,68],[68,69]],"faces":[{"face_id":45,"vert_ids":[66,63,62],"verts":[[54.7031,135.0211],[150.6506,135.0211],[139.7969,165.4117]]},{"face_id":48,"vert_ids":[63,69,65],"verts":[[95.9475,19.5368],[10.8538,85.0937],[41.2444,0.0]]},{"face_id":49,"vert_ids":[67,63,66],"verts":[[65.5569,104.6306],[150.6506,135.0211],[54.7031,135.0211]]},{"face_id":50,"vert_ids":[67,69,63],"verts":[[65.5569,104.6306],[10.8538,85.0937],[95.9475,19.5368]]},{"face_id":54,"vert_ids":[68,67,66],"verts":[[0.0,115.4843],[65.5569,104.6306],[54.7031,135.0211]]},{"face_id":55,"vert_ids":[69,67,68],"verts":[[10.8538,85.0937],[65.5569,104.6306],[0.0,115.4843]]}],"fold_convex":[true,true,true,true,true],"fold_edges":[[63,66],[63,69],[66,67],[67,68],[67,69]],"full_h":167.4453,"full_w":150.6506,"h":165.4117,"index":8,"n_faces":6,"n_tabs":3,"tabs":[{"edge":[62,66],"height_mm":7.0,"kind":"flap","number":34,"poly":[[139.7968,165.4117],[124.6784,167.4453],[65.1128,146.1719],[54.7031,135.0211]]},{"edge":[63,67],"height_mm":7.0,"kind":"flap","number":35,"poly":[[150.6506,135.0211],[140.2409,123.8703],[80.6753,102.597],[65.5569,104.6306]]},{"edge":[65,69],"height_mm":7.0,"kind":"flap","number":36,"poly":[[41.2444,0.0],[30.0936,10.4097],[8.8202,69.9753],[10.8538,85.0937]]}],"w":150.6506},{"cut_edges":[[70,71],[70,74],[71,73],[72,76],[73,77],[74,76],[76,77]],"faces":[{"face_id":56,"vert_ids":[71,73,70],"verts":[[6.6262,199.4325],[6.6262,121.983],[12.435,199.4325]]},{"face_id":58,"vert_ids":[70,73,72],"verts":[[12.435,199.4325],[6.6262,121.983],[12.435,121.983]]},{"face_id":59,"vert_ids":[72,74,70],"verts":[[12.435,121.983],[128.6092,199.4325],[12.435,199.4325]]},{"face_id":63,"vert_ids":[73,77,72],"verts":[[6.6262,121.983],[6.6262,5.8087],[12.435,121.983]]},{"face_id":64,"vert_ids":[76,74,72],"verts":[[128.6092,121.983],[128.6092,199.4325],[12.435,121.983]]},{"face_id":65,"vert_ids":[72,77,76],"verts":[[12.435,121.983],[6.6262,5.8087],[12.435,5.8087]]}],"fold_convex":[true,true,true,true,true],"fold_edges":[[70,72],[70,73],[72,73],[72,74],[72,77]],"full_h":200.4238,"full_w":135.983,"h":193.6238,"index":9,"n_faces":6,"n_tabs":5,"tabs":[{"edge":[70,71],"height_mm":3.4,"kind":"flap","number":37,"poly":[[12.435,199.4325],[11.5636,202.8325],[7.4976,202.8325],[6.6262,199.4325]]},{"edge":[71,73],"height_mm":7.0,"kind":"flap","number":38,"poly":[[6.6262,199.4325],[-0.3738,187.8151],[-0.3738,133.6004],[6.6262,121.983]]},{"edge":[72,76],"height_mm":7.0,"kind":"flap","number":39,"poly":[[12.435,121.983],[29.8611,114.983],[111.1831,114.983],[128.6092,121.983]]},{"edge":[74,76],"height_mm":7.0,"kind":"flap","number":40,"poly":[[128.6092,199.4325],[135.6092,187.8151],[135.6092,133.6004],[128.6092,121.983]]},{"edge":[76,77],"height_mm":3.4,"kind":"flap","number":41,"poly":[[12.435,5.8087],[11.5636,2.4087],[7.4976,2.4087],[6.6262,5.8087]]}],"w":121.983},{"cut_edges":[[78,79],[78,82],[79,81],[79,83],[81,85],[82,84],[84,85]],"faces":[{"face_id":57,"vert_ids":[82,79,78],"verts":[[125.6985,116.3194],[125.6985,0.0],[131.5,0.29]]},{"face_id":60,"vert_ids":[79,85,81],"verts":[[3.8676,110.2279],[116.0294,193.3823],[0.0,187.5808]]},{"face_id":61,"vert_ids":[83,79,82],"verts":[[119.897,116.0294],[125.6985,0.0],[125.6985,116.3194]]},{"face_id":62,"vert_ids":[83,85,79],"verts":[[119.897,116.0294],[116.0294,193.3823],[3.8676,110.2279]]},{"face_id":66,"vert_ids":[84,83,82],"verts":[[121.8309,193.6723],[119.897,116.0294],[125.6985,116.3194]]},{"face_id":67,"vert_ids":[85,83,84],"verts":[[116.0294,193.3823],[119.897,116.0294],[121.8309,193.6723]]}],"fold_convex":[true,true,true,true,true],"fold_edges":[[79,82],[79,85],[82,83],[83,84],[83,85]],"full_h":199.5033,"full_w":137.621,"h":193.6723,"index":10,"n_faces":6,"n_tabs":3,"tabs":[{"edge":[78,82],"height_mm":7.0,"kind":"flap","number":42,"poly":[[131.5,0.29],[137.621,18.0441],[133.56,99.2645],[125.6985,116.3194]]},{"edge":[79,83],"height_mm":7.0,"kind":"flap","number":43,"poly":[[125.6985,0.0],[117.837,17.0548],[113.776,98.2754],[119.897,116.0294]]},{"edge":[81,85],"height_mm":7.0,"kind":"flap","number":44,"poly":[[0.0,187.5808],[17.0549,195.4423],[98.2754,199.5033],[116.0294,193.3823]]}],"w":131.5},{"cut_edges":[[87,91],[88,91],[89,90],[90,91]],"faces":[{"face_id":68,"vert_ids":[87,86,89],"verts":[[55.925,48.0187],[103.9436,48.0187],[103.9436,96.0375]]},{"face_id":69,"vert_ids":[87,89,88],"verts":[[55.925,48.0187],[103.9436,96.0375],[51.097,100.8654]]},{"face_id":70,"vert_ids":[89,86,90],"verts":[[103.9436,96.0375],[103.9436,48.0187],[151.9623,48.0187]]},{"face_id":71,"vert_ids":[89,90,88],"verts":[[103.9436,96.0375],[65.421,151.9623],[51.097,100.8654]]},{"face_id":72,"vert_ids":[90,86,91],"verts":[[151.9623,48.0187],[103.9436,48.0187],[103.9436,0.0]]},{"face_id":73,"vert_ids":[90,91,88],"verts":[[65.421,151.9623],[3.4415,124.2113],[51.097,100.8654]]},{"face_id":74,"vert_ids":[91,86,87],"verts":[[103.9436,0.0],[103.9436,48.0187],[55.925,48.0187]]},{"face_id":75,"vert_ids":[91,87,88],"verts":[[0.0,86.5414],[55.925,48.0187],[51.097,100.8654]]}],"fold_convex":[true,true,true,true,true,true,true,true],"fold_edges":[[86,87],[86,89],[86,90],[86,91],[87,88],[87,89],[88,89],[88,90]],"full_h":151.9623,"full_w":151.9623,"h":151.9623,"index":11,"n_faces":8,"n_tabs":4,"tabs":[{"edge":[87,91],"height_mm":7.0,"kind":"flap","number":45,"poly":[[55.925,48.0187],[58.1779,35.8663],[91.7911,2.2531],[103.9437,0.0]]},{"edge":[88,91],"height_mm":7.0,"kind":"flap","number":46,"poly":[[51.097,100.8654],[40.869,98.0811],[7.5103,114.4232],[3.4415,124.2113]]},{"edge":[89,90],"height_mm":7.0,"kind":"flap","number":47,"poly":[[103.9437,96.0375],[116.0962,93.7844],[149.7093,60.1713],[151.9623,48.0187]]},{"edge":[90,91],"height_mm":7.0,"kind":"flap","number":48,"poly":[[151.9623,48.0187],[149.7093,35.8662],[116.0962,2.253],[103.9437,0.0]]}],"w":151.9623}],"score":{"is_buildable":true,"overlaps":0,"papers_exceeded":0,"parts":12,"sub_min_tabs":0},"sheets":[{"page_index":0,"paper_h_mm":297.0,"paper_w_mm":210.0,"placements":[[0,0.0,0.0,0.0]]},{"page_index":1,"paper_h_mm":297.0,"paper_w_mm":210.0,"placements":[[1,0.0,0.0,0.0]]},{"page_index":2,"paper_h_mm":297.0,"paper_w_mm":210.0,"placements":[[2,0.0,0.0,0.0]]},{"page_index":3,"paper_h_mm":297.0,"paper_w_mm":210.0,"placements":[[3,0.0,0.0,0.0]]},{"page_index":4,"paper_h_mm":297.0,"paper_w_mm":210.0,"placements":[[4,0.0,0.0,0.0]]},{"page_index":5,"paper_h_mm":297.0,"paper_w_mm":210.0,"placements":[[5,0.0,0.0,0.0]]},{"page_index":6,"paper_h_mm":297.0,"paper_w_mm":210.0,"placements":[[6,0.0,0.0,0.0]]},{"page_index":7,"paper_h_mm":297.0,"paper_w_mm":210.0,"placements":[[7,0.0,0.0,0.0]]},{"page_index":8,"paper_h_mm":297.0,"paper_w_mm":210.0,"placements":[[8,0.0,0.0,0.0]]},{"page_index":9,"paper_h_mm":297.0,"paper_w_mm":210.0,"placements":[[9,0.0,0.0,0.0]]},{"page_index":10,"paper_h_mm":297.0,"paper_w_mm":210.0,"placements":[[10,0.0,0.0,0.0]]},{"page_index":11,"paper_h_mm":297.0,"paper_w_mm":210.0,"placements":[[11,0.0,0.0,0.0]]}]}